novamber/__init__.py
novamber/_core/__init__.py
novamber/_core/bond_graph.py
novamber/_core/energy_calculator.py
novamber/_forcefield/__init__.py
novamber/_forcefield/angles.py
novamber/_forcefield/bonds.py
novamber/_forcefield/dihedrals.py
novamber/_forcefield/forcefield.py
novamber/_forcefield/interaction.py
novamber/_forcefield/nonbonded.py
novamber/_forcefield/particles.py
novamber/_misc/__init__.py
novamber/_misc/utils.py
novamber/_parsers/__init__.py
novamber/_parsers/_tables.py
novamber/_parsers/ffparser.py
novamber/_parsers/ffparser_xml.py
novamber/_parsers/pdb_postprocess.py
novamber-0.1.0.dist-info/licenses/LICENSE.md
novamber-0.1.0.dist-info/METADATA
novamber-0.1.0.dist-info/WHEEL
novamber-0.1.0.dist-info/top_level.txt
novamber-0.1.0.dist-info/RECORD
